[{"id":1,"name":"Dave Bittle","win":1,"loss":14,"rate":0.0666666666667},{"id":2,"name":"Daniel Boos","win":3,"loss":15,"rate":0.166666666667},{"id":3,"name":"Michael Bray","win":4,"loss":24,"rate":0.142857142857},{"id":5,"name":"Alisa Burdeyny","win":7,"loss":6,"rate":0.538461538462},{"id":6,"name":"Nat Burgwyn","win":3,"loss":0,"rate":1},{"id":7,"name":"Charles Chao","win":23,"loss":0,"rate":1},{"id":8,"name":"Anthony Chen","win":2,"loss":2,"rate":0.5},{"id":9,"name":"Kevin Chiu","win":23,"loss":2,"rate":0.92},{"id":10,"name":"Seth Clark","win":3,"loss":6,"rate":0.333333333333},{"id":11,"name":"Zachary Clay","win":0,"loss":25,"rate":0},{"id":12,"name":"Elizabeth Dabbs","win":2,"loss":7,"rate":0.222222222222},{"id":14,"name":"Mike Hess","win":8,"loss":4,"rate":0.666666666667},{"id":15,"name":"Noelle Jung","win":4,"loss":11,"rate":0.266666666667},{"id":16,"name":"Sunggyun Kim","win":2,"loss":3,"rate":0.4},{"id":17,"name":"Waikay Kong","win":2,"loss":5,"rate":0.285714285714},{"id":18,"name":"Samuel Levine","win":12,"loss":17,"rate":0.413793103448},{"id":19,"name":"Kevin Li","win":14,"loss":2,"rate":0.875},{"id":20,"name":"Nathan Mellis","win":4,"loss":1,"rate":0.8},{"id":22,"name":"Andrew Mshar","win":1,"loss":0,"rate":1},{"id":23,"name":"Virginia Nguyen","win":1,"loss":0,"rate":1},{"id":24,"name":"Martin Press","win":10,"loss":1,"rate":0.909090909091},{"id":25,"name":"Dan Rich","win":2,"loss":3,"rate":0.4},{"id":26,"name":"Alan Shih","win":26,"loss":5,"rate":0.838709677419},{"id":27,"name":"David Trinh","win":1,"loss":1,"rate":0.5},{"id":28,"name":"Andrew Vogel","win":0,"loss":4,"rate":0},{"id":29,"name":"James Worcester","win":0,"loss":15,"rate":0},{"id":30,"name":"Peter Yang","win":4,"loss":1,"rate":0.8},{"id":31,"name":"Santi Pikula","win":77,"loss":0,"rate":1}]